jumpstarter_testing/__init__.py
jumpstarter_testing/py.typed
jumpstarter_testing/pytest.py
jumpstarter_testing/pytest_test.py
jumpstarter_testing-0.7.4.dist-info/METADATA
jumpstarter_testing-0.7.4.dist-info/WHEEL
jumpstarter_testing-0.7.4.dist-info/RECORD
