Metadata-Version: 2.4
Name: jumpstarter-testing
Version: 0.7.4
Project-URL: Homepage, https://jumpstarter.dev
Project-URL: source_archive, https://github.com/jumpstarter-dev/repo/archive/c5d38de69eadbb8eb0388bcfe3430a679fff0059.zip
Author-email: Kirk Brauer <kbrauer@hatci.com>
License-Expression: Apache-2.0
Requires-Python: >=3.11
Requires-Dist: jumpstarter==0.7.4
Requires-Dist: pytest-anyio>=0.0.0
Requires-Dist: pytest-asyncio>=0.0.0
Requires-Dist: pytest-cov>=5.0.0
Requires-Dist: pytest>=8.3.2
